devtransfer/__init__.py
devtransfer/_nbdev.py
devtransfer/api.py
devtransfer/auth.py
devtransfer/compression.py
devtransfer/conf.py
devtransfer/core.py
devtransfer/downloader.py
devtransfer/encryption.py
devtransfer/exceptions.py
devtransfer/formatting.py
devtransfer/http.py
devtransfer/parsers.py
devtransfer/uploader.py
devtransfer/utils.py
devtransfer-0.0.4.dist-info/LICENSE
devtransfer-0.0.4.dist-info/METADATA
devtransfer-0.0.4.dist-info/WHEEL
devtransfer-0.0.4.dist-info/entry_points.txt
devtransfer-0.0.4.dist-info/top_level.txt
devtransfer-0.0.4.dist-info/RECORD
